aevol/__init__.py
aevol/cli/__init__.py
aevol/cli/aevol_ui_build_views.py
aevol/models/__init__.py
aevol/models/environment.py
aevol/models/genome_roi.py
aevol/models/individual.py
aevol/models/phenotypic_function.py
aevol/models/population.py
aevol/models/protein.py
aevol/models/rna.py
aevol/visual/__init__.py
aevol/visual/draw.py
aevol/visual/gene_view.py
aevol/visual/genome_view.py
aevol/visual/grid_view.py
aevol/visual/phenotype_view.py
aevol/visual/proteome_view.py
aevol/visual/rna_view.py
aevol/visual/utils.py
aevol-0.5.3.dist-info/LICENSE
aevol-0.5.3.dist-info/METADATA
aevol-0.5.3.dist-info/WHEEL
aevol-0.5.3.dist-info/entry_points.txt
aevol-0.5.3.dist-info/RECORD
