Metadata-Version: 2.1
Name: aevol
Version: 0.5.3
Summary: Aevol python package
Home-page: https://www.aevol.fr/
License: GPL-3.0-or-later
Author: David Parsons
Author-email: david.parsons@inria.fr
Requires-Python: >=3.9,<4.0
Classifier: License :: OSI Approved :: GNU General Public License v3 or later (GPLv3+)
Classifier: Programming Language :: Python :: 3
Classifier: Programming Language :: Python :: 3.9
Classifier: Programming Language :: Python :: 3.10
Classifier: Programming Language :: Python :: 3.11
Classifier: Programming Language :: Python :: 3.12
Requires-Dist: importlib-metadata (>=8.5,<9.0)
Requires-Dist: matplotlib (>=3.7.2,<4.0.0)
Requires-Dist: pandas (>=2.1.0,<3.0.0)
Project-URL: Repository, https://gitlab.inria.fr/aevol/aevol-ui/aevol-py
